wolta/__init__.py
wolta/data_tools.py
wolta/feature_tools.py
wolta/model_tools.py
wolta/progressive_tools.py
wolta/visual_tools.py
wolta-0.3.7.dist-info/LICENSE.txt
wolta-0.3.7.dist-info/METADATA
wolta-0.3.7.dist-info/WHEEL
wolta-0.3.7.dist-info/top_level.txt
wolta-0.3.7.dist-info/RECORD
