Metadata-Version: 2.1
Name: wolta
Version: 0.3.7
Summary: Data Science Library
Author: iamalreadynoob
Author-email: <sadikefe69@gmail.com>
Keywords: python,machine,learning,machine learning,data science,data
Classifier: Development Status :: 1 - Planning
Classifier: Intended Audience :: Developers
Classifier: Programming Language :: Python :: 3
Classifier: Operating System :: Unix
Classifier: Operating System :: MacOS :: MacOS X
Classifier: Operating System :: Microsoft :: Windows
License-File: LICENSE.txt
Requires-Dist: scikit-learn
Requires-Dist: pandas
Requires-Dist: numpy
Requires-Dist: hyperopt
Requires-Dist: catboost
Requires-Dist: imblearn
Requires-Dist: lightgbm
Requires-Dist: matplotlib
Requires-Dist: opencv-python
